PyMouse_Qi/__init__.py
PyMouse_Qi/java_.py
PyMouse_Qi/mac.py
PyMouse_Qi/unix.py
PyMouse_Qi/windows.py
PyMouse_Qi-1.1.1.dist-info/METADATA
PyMouse_Qi-1.1.1.dist-info/WHEEL
PyMouse_Qi-1.1.1.dist-info/top_level.txt
PyMouse_Qi-1.1.1.dist-info/RECORD
