Metadata-Version: 2.1
Name: PyMouse-Qi
Version: 1.1.1
Summary: Cross-platform mouse control
Home-page: UNKNOWN
Author: Pepijn de Vos , modifier by Qi
Author-email: pypimail@protonmail.com
License: UNKNOWN
Platform: UNKNOWN
Classifier: Programming Language :: Python
Classifier: Intended Audience :: Developers
Classifier: License :: OSI Approved :: Apache Software License
Classifier: Operating System :: MacOS :: MacOS X
Classifier: Operating System :: Microsoft :: Windows
Classifier: Operating System :: Unix
Classifier: Topic :: Software Development :: Libraries :: Python Modules
